odoo8_addon_sale_delivery_split_date-8.0.1.2.0-py2.7-nspkg.pth
odoo8_addon_sale_delivery_split_date-8.0.1.2.0.dist-info/METADATA
odoo8_addon_sale_delivery_split_date-8.0.1.2.0.dist-info/RECORD
odoo8_addon_sale_delivery_split_date-8.0.1.2.0.dist-info/WHEEL
odoo8_addon_sale_delivery_split_date-8.0.1.2.0.dist-info/namespace_packages.txt
odoo8_addon_sale_delivery_split_date-8.0.1.2.0.dist-info/top_level.txt
odoo_addons/sale_delivery_split_date/README.rst
odoo_addons/sale_delivery_split_date/__init__.py
odoo_addons/sale_delivery_split_date/__openerp__.py
odoo_addons/sale_delivery_split_date/i18n/it.po
odoo_addons/sale_delivery_split_date/i18n/sale_delivery_split_date.pot
odoo_addons/sale_delivery_split_date/models/__init__.py
odoo_addons/sale_delivery_split_date/models/sale_order.py
odoo_addons/sale_delivery_split_date/models/sale_order_line.py
odoo_addons/sale_delivery_split_date/models/stock_picking.py
odoo_addons/sale_delivery_split_date/static/description/icon.png
odoo_addons/sale_delivery_split_date/tests/__init__.py
odoo_addons/sale_delivery_split_date/tests/test_sale_delivery.py
odoo_addons/sale_delivery_split_date/views/stock_picking.xml
