Metadata-Version: 2.1
Name: odoo8-addon-sale-delivery-split-date
Version: 8.0.1.2.0
Summary: Sale Deliveries split by date
Home-page: https://github.com/OCA/sale-workflow
Author: Agile Business Group, Odoo Community Association (OCA)
Author-email: support@odoo-community.org
License: AGPL-3
Platform: UNKNOWN
Classifier: Programming Language :: Python
Classifier: Framework :: Odoo
Classifier: License :: OSI Approved :: GNU Affero General Public License v3
Requires-Python: ~=2.7
Requires-Dist: odoo8-addon-sale-order-line-date
Requires-Dist: odoo8-addon-sale-procurement-group-by-line
Requires-Dist: odoo (<9.0a,>=8.0a)
